{
  "id": "297:8135",
  "name": "ic:sharp-open-with",
  "type": "FRAME",
  "scrollBehavior": "SCROLLS",
  "children": [
    {
      "id": "297:8136",
      "name": "Vector",
      "type": "VECTOR",
      "scrollBehavior": "SCROLLS",
      "blendMode": "PASS_THROUGH",
      "fills": [
        {
          "blendMode": "NORMAL",
          "type": "SOLID",
          "color": {
            "r": 0,
            "g": 0,
            "b": 0,
            "a": 1
          }
        }
      ],
      "strokes": [],
      "strokeWeight": 1,
      "strokeAlign": "INSIDE",
      "absoluteBoundingBox": {
        "x": 382,
        "y": -14267,
        "width": 22,
        "height": 22
      },
      "absoluteRenderBounds": {
        "x": 382,
        "y": -14267,
        "width": 22,
        "height": 22
      },
      "constraints": {
        "vertical": "SCALE",
        "horizontal": "SCALE"
      },
      "effects": [],
      "interactions": []
    }
  ],
  "blendMode": "PASS_THROUGH",
  "clipsContent": true,
  "background": [
    {
      "blendMode": "NORMAL",
      "visible": false,
      "type": "SOLID",
      "color": {
        "r": 1,
        "g": 1,
        "b": 1,
        "a": 1
      }
    }
  ],
  "fills": [
    {
      "blendMode": "NORMAL",
      "visible": false,
      "type": "SOLID",
      "color": {
        "r": 1,
        "g": 1,
        "b": 1,
        "a": 1
      }
    }
  ],
  "strokes": [],
  "strokeWeight": 1,
  "strokeAlign": "INSIDE",
  "backgroundColor": {
    "r": 0,
    "g": 0,
    "b": 0,
    "a": 0
  },
  "absoluteBoundingBox": {
    "x": 381,
    "y": -14268,
    "width": 24,
    "height": 24
  },
  "absoluteRenderBounds": {
    "x": 381,
    "y": -14268,
    "width": 24,
    "height": 24
  },
  "preserveRatio": true,
  "targetAspectRatio": {
    "x": 24,
    "y": 24
  },
  "constraints": {
    "vertical": "TOP",
    "horizontal": "LEFT"
  },
  "effects": [],
  "interactions": []
}