{
  "type": "instance",
  "name": "Property 1=Enabled",
  "id": "I337:6095;3557:177773",
  "properties": {
    "isInstance": true,
    "componentId": "296:4423",
    "componentName": "Property 1=Enabled",
    "componentProperties": {
      "Value#3008:25": {
        "value": "48",
        "type": "TEXT"
      },
      "Status#3008:29": {
        "value": "296:3313",
        "type": "INSTANCE_SWAP",
        "preferredValues": [
          {
            "type": "COMPONENT_SET",
            "key": "bdd367dfe9e8c34421f1a16694d1d7b071970c20"
          }
        ]
      },
      "Text#3617:0": {
        "value": "Label",
        "type": "TEXT"
      },
      "Left Icon#3617:5": {
        "value": true,
        "type": "BOOLEAN"
      },
      "Badge#3617:4": {
        "value": true,
        "type": "BOOLEAN"
      },
      "Avatar#3617:3": {
        "value": false,
        "type": "BOOLEAN"
      },
      "Label#3617:1": {
        "value": true,
        "type": "BOOLEAN"
      },
      "Icon#3617:2": {
        "value": "296:2810",
        "type": "INSTANCE_SWAP",
        "preferredValues": [
          {
            "type": "COMPONENT",
            "key": "ed320f52f7ec385f4653bf00069728a214143b01"
          }
        ]
      },
      "Property 1": {
        "value": "Enabled",
        "type": "VARIANT",
        "boundVariables": {}
      }
    },
    "visible": false,
    "constraints": {
      "horizontal": "MIN",
      "vertical": "MIN"
    },
    "suggestedClassName": "property-1-enabled",
    "locked": false,
    "isMask": false,
    "exportSettings": []
  },
  "styles": {
    "width": 109,
    "height": 32,
    "x": 943,
    "y": 0,
    "border": {
      "width": 1,
      "style": "CENTER",
      "color": {
        "r": 222,
        "g": 227,
        "b": 236,
        "a": 1
      }
    },
    "borderRadius": 4,
    "opacity": 1,
    "layout": {
      "mode": "HORIZONTAL",
      "primaryAxisAlignItems": "MIN",
      "counterAxisAlignItems": "CENTER",
      "padding": {
        "top": 4,
        "right": 8,
        "bottom": 4,
        "left": 8
      },
      "itemSpacing": 8
    }
  },
  "metadata": {
    "figmaId": "I337:6095;3557:177773",
    "figmaType": "INSTANCE",
    "figmaPath": [
      "MVP",
      "Auto Layout Vertical",
      "Auto Layout Vertical",
      "User Type=Host",
      "Property 1=Enabled"
    ]
  },
  "children": [
    {
      "type": "instance",
      "name": "Statuses",
      "id": "I337:6095;3557:177773;3006:37504",
      "properties": {
        "isInstance": true,
        "componentId": "296:3313",
        "componentName": "Type=Open, Size=Small",
        "componentProperties": {
          "Background color#3006:3": {
            "value": false,
            "type": "BOOLEAN"
          },
          "Text#2949:0": {
            "value": "Label",
            "type": "TEXT"
          },
          "Type": {
            "value": "Open",
            "type": "VARIANT",
            "boundVariables": {}
          },
          "Size": {
            "value": "Small",
            "type": "VARIANT",
            "boundVariables": {}
          }
        },
        "visible": true,
        "constraints": {
          "horizontal": "MIN",
          "vertical": "MIN"
        },
        "suggestedClassName": "statuses",
        "locked": false,
        "isMask": false,
        "exportSettings": []
      },
      "styles": {
        "width": 57,
        "height": 24,
        "x": 8,
        "y": 4,
        "borderRadius": 0,
        "opacity": 1,
        "layout": {
          "mode": "HORIZONTAL",
          "primaryAxisAlignItems": "MIN",
          "counterAxisAlignItems": "CENTER",
          "padding": {
            "top": 0,
            "right": 0,
            "bottom": 0,
            "left": 0
          },
          "itemSpacing": 4
        }
      },
      "metadata": {
        "figmaId": "I337:6095;3557:177773;3006:37504",
        "figmaType": "INSTANCE",
        "figmaPath": [
          "MVP",
          "Auto Layout Vertical",
          "Auto Layout Vertical",
          "User Type=Host",
          "Property 1=Enabled",
          "Statuses"
        ]
      },
      "children": [
        {
          "type": "instance",
          "name": "bookmark",
          "id": "I337:6095;3557:177773;3006:37504;2990:24410",
          "properties": {
            "isInstance": true,
            "componentId": "296:4419",
            "componentName": "bookmark",
            "componentProperties": {},
            "visible": true,
            "constraints": {
              "horizontal": "MIN",
              "vertical": "MIN"
            },
            "suggestedClassName": "bookmark",
            "locked": false,
            "isMask": false,
            "exportSettings": []
          },
          "styles": {
            "width": 16,
            "height": 16,
            "x": 0,
            "y": 4,
            "borderRadius": 0,
            "opacity": 1
          },
          "metadata": {
            "figmaId": "I337:6095;3557:177773;3006:37504;2990:24410",
            "figmaType": "INSTANCE",
            "figmaPath": [
              "MVP",
              "Auto Layout Vertical",
              "Auto Layout Vertical",
              "User Type=Host",
              "Property 1=Enabled",
              "Statuses",
              "bookmark"
            ]
          },
          "children": [
            {
              "type": "vector",
              "name": "Vector",
              "id": "I337:6095;3557:177773;3006:37504;2990:24410;2919:26210",
              "properties": {
                "visible": true,
                "constraints": {
                  "horizontal": "SCALE",
                  "vertical": "SCALE"
                },
                "suggestedClassName": "vector",
                "locked": false,
                "isMask": false,
                "exportSettings": []
              },
              "styles": {
                "width": 16,
                "height": 16,
                "x": 0,
                "y": 0,
                "borderRadius": 0,
                "opacity": 1
              },
              "metadata": {
                "figmaId": "I337:6095;3557:177773;3006:37504;2990:24410;2919:26210",
                "figmaType": "VECTOR",
                "figmaPath": [
                  "MVP",
                  "Auto Layout Vertical",
                  "Auto Layout Vertical",
                  "User Type=Host",
                  "Property 1=Enabled",
                  "Statuses",
                  "bookmark",
                  "Vector"
                ]
              },
              "vector": {
                "network": {
                  "vertices": [
                    {
                      "x": 0,
                      "y": 0,
                      "strokeCap": "NONE",
                      "strokeJoin": "MITER",
                      "cornerRadius": 0,
                      "handleMirroring": "NONE"
                    },
                    {
                      "x": 16,
                      "y": 0,
                      "strokeCap": "NONE",
                      "strokeJoin": "MITER",
                      "cornerRadius": 0,
                      "handleMirroring": "NONE"
                    },
                    {
                      "x": 16,
                      "y": 16,
                      "strokeCap": "NONE",
                      "strokeJoin": "MITER",
                      "cornerRadius": 0,
                      "handleMirroring": "NONE"
                    },
                    {
                      "x": 0,
                      "y": 16,
                      "strokeCap": "NONE",
                      "strokeJoin": "MITER",
                      "cornerRadius": 0,
                      "handleMirroring": "NONE"
                    }
                  ],
                  "segments": [
                    {
                      "start": 0,
                      "end": 1,
                      "tangentStart": {
                        "x": 0,
                        "y": 0
                      },
                      "tangentEnd": {
                        "x": 0,
                        "y": 0
                      }
                    },
                    {
                      "start": 1,
                      "end": 2,
                      "tangentStart": {
                        "x": 0,
                        "y": 0
                      },
                      "tangentEnd": {
                        "x": 0,
                        "y": 0
                      }
                    },
                    {
                      "start": 2,
                      "end": 3,
                      "tangentStart": {
                        "x": 0,
                        "y": 0
                      },
                      "tangentEnd": {
                        "x": 0,
                        "y": 0
                      }
                    },
                    {
                      "start": 3,
                      "end": 0,
                      "tangentStart": {
                        "x": 0,
                        "y": 0
                      },
                      "tangentEnd": {
                        "x": 0,
                        "y": 0
                      }
                    }
                  ],
                  "regions": [
                    {
                      "windingRule": "NONZERO",
                      "loops": [
                        [
                          0,
                          1,
                          2,
                          3
                        ]
                      ],
                      "fillStyleId": "",
                      "fills": []
                    }
                  ]
                },
                "vectorPaths": [
                  {
                    "windingRule": "NONZERO",
                    "data": "M 0 0 L 16 0 L 16 16 L 0 16 L 0 0 Z"
                  }
                ],
                "fillStyles": [],
                "strokeStyles": [],
                "strokeProperties": null
              }
            },
            {
              "type": "vector",
              "name": "Vector",
              "id": "I337:6095;3557:177773;3006:37504;2990:24410;2919:26211",
              "properties": {
                "visible": true,
                "constraints": {
                  "horizontal": "SCALE",
                  "vertical": "SCALE"
                },
                "suggestedClassName": "vector",
                "locked": false,
                "isMask": false,
                "exportSettings": []
              },
              "styles": {
                "width": 9,
                "height": 12,
                "x": 3,
                "y": 2,
                "backgroundColor": {
                  "r": 98,
                  "g": 121,
                  "b": 149,
                  "a": 1
                },
                "backgroundColorHex": "#627995",
                "borderRadius": 0,
                "opacity": 1
              },
              "metadata": {
                "figmaId": "I337:6095;3557:177773;3006:37504;2990:24410;2919:26211",
                "figmaType": "VECTOR",
                "figmaPath": [
                  "MVP",
                  "Auto Layout Vertical",
                  "Auto Layout Vertical",
                  "User Type=Host",
                  "Property 1=Enabled",
                  "Statuses",
                  "bookmark",
                  "Vector"
                ]
              },
              "vector": {
                "network": {
                  "vertices": [
                    {
                      "x": 8.000000544956752,
                      "y": 0,
                      "strokeCap": "NONE",
                      "strokeJoin": "MITER",
                      "cornerRadius": 0,
                      "handleMirroring": "NONE"
                    },
                    {
                      "x": 1.3333334241594588,
                      "y": 0,
                      "strokeCap": "NONE",
                      "strokeJoin": "MITER",
                      "cornerRadius": 0,
                      "handleMirroring": "NONE"
                    },
                    {
                      "x": 0,
                      "y": 1.3333333333333333,
                      "strokeCap": "NONE",
                      "strokeJoin": "MITER",
                      "cornerRadius": 0,
                      "handleMirroring": "NONE"
                    },
                    {
                      "x": 0,
                      "y": 12,
                      "strokeCap": "NONE",
                      "strokeJoin": "MITER",
                      "cornerRadius": 0,
                      "handleMirroring": "NONE"
                    },
                    {
                      "x": 4.6666669845581055,
                      "y": 10,
                      "strokeCap": "NONE",
                      "strokeJoin": "MITER",
                      "cornerRadius": 0,
                      "handleMirroring": "NONE"
                    },
                    {
                      "x": 9.333333969116211,
                      "y": 12,
                      "strokeCap": "NONE",
                      "strokeJoin": "MITER",
                      "cornerRadius": 0,
                      "handleMirroring": "NONE"
                    },
                    {
                      "x": 9.333333969116211,
                      "y": 1.3333333333333333,
                      "strokeCap": "NONE",
                      "strokeJoin": "MITER",
                      "cornerRadius": 0,
                      "handleMirroring": "NONE"
                    }
                  ],
                  "segments": [
                    {
                      "start": 0,
                      "end": 1,
                      "tangentStart": {
                        "x": 0,
                        "y": 0
                      },
                      "tangentEnd": {
                        "x": 0,
                        "y": 0
                      }
                    },
                    {
                      "start": 1,
                      "end": 2,
                      "tangentStart": {
                        "x": -0.7333333991822754,
                        "y": 0
                      },
                      "tangentEnd": {
                        "x": 0,
                        "y": -0.7333333492279053
                      }
                    },
                    {
                      "start": 2,
                      "end": 3,
                      "tangentStart": {
                        "x": 0,
                        "y": 0
                      },
                      "tangentEnd": {
                        "x": 0,
                        "y": 0
                      }
                    },
                    {
                      "start": 3,
                      "end": 4,
                      "tangentStart": {
                        "x": 0,
                        "y": 0
                      },
                      "tangentEnd": {
                        "x": 0,
                        "y": 0
                      }
                    },
                    {
                      "start": 4,
                      "end": 5,
                      "tangentStart": {
                        "x": 0,
                        "y": 0
                      },
                      "tangentEnd": {
                        "x": 0,
                        "y": 0
                      }
                    },
                    {
                      "start": 5,
                      "end": 6,
                      "tangentStart": {
                        "x": 0,
                        "y": 0
                      },
                      "tangentEnd": {
                        "x": 0,
                        "y": 0
                      }
                    },
                    {
                      "start": 6,
                      "end": 0,
                      "tangentStart": {
                        "x": 0,
                        "y": -0.7333333492279053
                      },
                      "tangentEnd": {
                        "x": 0.7333333991822754,
                        "y": 0
                      }
                    }
                  ],
                  "regions": [
                    {
                      "windingRule": "NONZERO",
                      "loops": [
                        [
                          0,
                          1,
                          2,
                          3,
                          4,
                          5,
                          6
                        ]
                      ],
                      "fillStyleId": "S:c45b0aca44e24c6b6ebf597d543825db0465e619,2955:53",
                      "fills": [
                        {
                          "type": "SOLID",
                          "visible": true,
                          "opacity": 1,
                          "blendMode": "NORMAL",
                          "color": {
                            "r": 0.38268789649009705,
                            "g": 0.4736708402633667,
                            "b": 0.5833170413970947
                          },
                          "boundVariables": {}
                        }
                      ]
                    }
                  ]
                },
                "vectorPaths": [
                  {
                    "windingRule": "NONZERO",
                    "data": "M 8.000000544956752 0 L 1.3333334241594588 0 C 0.6000000249771834 0 0 0.599999984105428 0 1.3333333333333333 L 0 12 L 4.6666669845581055 10 L 9.333333969116211 12 L 9.333333969116211 1.3333333333333333 C 9.333333969116211 0.599999984105428 8.733333944139027 0 8.000000544956752 0 Z"
                  }
                ],
                "fillStyles": [
                  {
                    "type": "SOLID",
                    "visible": true,
                    "opacity": 1,
                    "color": {
                      "r": 98,
                      "g": 121,
                      "b": 149,
                      "a": 1
                    }
                  }
                ],
                "strokeStyles": [],
                "strokeProperties": null
              }
            }
          ]
        },
        {
          "type": "text",
          "name": "Open for bids",
          "id": "I337:6095;3557:177773;3006:37504;2990:24411",
          "properties": {
            "text": "Saved",
            "visible": true,
            "constraints": {
              "horizontal": "MIN",
              "vertical": "MIN"
            },
            "suggestedClassName": "open-for-bids",
            "locked": false,
            "isMask": false,
            "exportSettings": []
          },
          "styles": {
            "width": 37,
            "height": 24,
            "x": 20,
            "y": 0,
            "backgroundColor": {
              "r": 98,
              "g": 121,
              "b": 149,
              "a": 1
            },
            "backgroundColorHex": "#627995",
            "opacity": 1,
            "typography": {
              "fontFamily": "Inter",
              "fontSize": 12,
              "fontWeight": 500,
              "lineHeight": {
                "unit": "PIXELS",
                "value": 24
              },
              "letterSpacing": {
                "unit": "PERCENT",
                "value": 2
              },
              "textAlign": "LEFT",
              "verticalAlign": "CENTER",
              "textCase": "ORIGINAL",
              "textDecoration": "NONE",
              "color": {
                "r": 98,
                "g": 121,
                "b": 149,
                "a": 1
              }
            }
          },
          "metadata": {
            "figmaId": "I337:6095;3557:177773;3006:37504;2990:24411",
            "figmaType": "TEXT",
            "figmaPath": [
              "MVP",
              "Auto Layout Vertical",
              "Auto Layout Vertical",
              "User Type=Host",
              "Property 1=Enabled",
              "Statuses",
              "Open for bids"
            ]
          }
        },
        {
          "type": "frame",
          "name": "Background color",
          "id": "I337:6095;3557:177773;3006:37504;2990:24409",
          "properties": {
            "visible": false,
            "constraints": {
              "horizontal": "STRETCH",
              "vertical": "STRETCH"
            },
            "suggestedClassName": "background-color",
            "locked": false,
            "isMask": false,
            "exportSettings": []
          },
          "styles": {
            "width": 57,
            "height": 24,
            "x": 0,
            "y": 0,
            "backgroundColor": {
              "r": 228,
              "g": 245,
              "b": 252,
              "a": 1
            },
            "backgroundColorHex": "#e4f5fc",
            "borderRadius": 100,
            "opacity": 1,
            "layout": {
              "mode": "HORIZONTAL",
              "primaryAxisAlignItems": "MIN",
              "counterAxisAlignItems": "CENTER",
              "padding": {
                "top": 0,
                "right": 4,
                "bottom": 0,
                "left": 4
              },
              "itemSpacing": 4
            }
          },
          "metadata": {
            "figmaId": "I337:6095;3557:177773;3006:37504;2990:24409",
            "figmaType": "FRAME",
            "figmaPath": [
              "MVP",
              "Auto Layout Vertical",
              "Auto Layout Vertical",
              "User Type=Host",
              "Property 1=Enabled",
              "Statuses",
              "Background color"
            ]
          },
          "children": []
        }
      ]
    },
    {
      "type": "instance",
      "name": "Badge",
      "id": "I337:6095;3557:177773;3617:58941",
      "properties": {
        "isInstance": true,
        "componentId": "296:2823",
        "componentName": "Property 1=Default",
        "componentProperties": {
          "Value#3665:0": {
            "value": "48",
            "type": "TEXT"
          },
          "Label#4012:7": {
            "value": "Label",
            "type": "TEXT"
          },
          "Property 1": {
            "value": "Default",
            "type": "VARIANT",
            "boundVariables": {}
          }
        },
        "visible": true,
        "constraints": {
          "horizontal": "MIN",
          "vertical": "MIN"
        },
        "suggestedClassName": "badge",
        "locked": false,
        "isMask": false,
        "exportSettings": []
      },
      "styles": {
        "width": 28,
        "height": 24,
        "x": 73,
        "y": 4,
        "backgroundColor": {
          "r": 239,
          "g": 240,
          "b": 246,
          "a": 1
        },
        "backgroundColorHex": "#eff0f6",
        "borderRadius": 14,
        "opacity": 1,
        "layout": {
          "mode": "HORIZONTAL",
          "primaryAxisAlignItems": "CENTER",
          "counterAxisAlignItems": "CENTER",
          "padding": {
            "top": 2,
            "right": 6,
            "bottom": 2,
            "left": 6
          },
          "itemSpacing": 8
        }
      },
      "metadata": {
        "figmaId": "I337:6095;3557:177773;3617:58941",
        "figmaType": "INSTANCE",
        "figmaPath": [
          "MVP",
          "Auto Layout Vertical",
          "Auto Layout Vertical",
          "User Type=Host",
          "Property 1=Enabled",
          "Badge"
        ]
      },
      "children": [
        {
          "type": "text",
          "name": "48",
          "id": "I337:6095;3557:177773;3617:58941;3528:67195",
          "properties": {
            "text": "48",
            "visible": true,
            "constraints": {
              "horizontal": "MIN",
              "vertical": "MIN"
            },
            "suggestedClassName": "48",
            "locked": false,
            "isMask": false,
            "exportSettings": []
          },
          "styles": {
            "width": 16,
            "height": 20,
            "x": 6,
            "y": 2,
            "backgroundColor": {
              "r": 98,
              "g": 121,
              "b": 149,
              "a": 1
            },
            "backgroundColorHex": "#627995",
            "opacity": 1,
            "typography": {
              "fontFamily": "Inter",
              "fontSize": 12,
              "fontWeight": 500,
              "lineHeight": {
                "unit": "PIXELS",
                "value": 20
              },
              "letterSpacing": {
                "unit": "PERCENT",
                "value": 2
              },
              "textAlign": "CENTER",
              "verticalAlign": "TOP",
              "textCase": "ORIGINAL",
              "textDecoration": "NONE",
              "color": {
                "r": 98,
                "g": 121,
                "b": 149,
                "a": 1
              }
            }
          },
          "metadata": {
            "figmaId": "I337:6095;3557:177773;3617:58941;3528:67195",
            "figmaType": "TEXT",
            "figmaPath": [
              "MVP",
              "Auto Layout Vertical",
              "Auto Layout Vertical",
              "User Type=Host",
              "Property 1=Enabled",
              "Badge",
              "48"
            ]
          }
        }
      ]
    }
  ]
}