{
  "id": "141:4062",
  "name": "Property 1=Multiple lines, Property 2=simple",
  "type": "COMPONENT",
  "scrollBehavior": "SCROLLS",
  "children": [
    {
      "id": "141:4059",
      "name": "Text content/Multiple lines/simple",
      "type": "TEXT",
      "scrollBehavior": "SCROLLS",
      "blendMode": "PASS_THROUGH",
      "fills": [
        {
          "blendMode": "NORMAL",
          "type": "SOLID",
          "color": {
            "r": 0.2980392277240753,
            "g": 0.3019607961177826,
            "b": 0.30588236451148987,
            "a": 1
          }
        }
      ],
      "strokes": [],
      "strokeWeight": 1,
      "strokeAlign": "OUTSIDE",
      "absoluteBoundingBox": {
        "x": 2014,
        "y": -14456,
        "width": 260,
        "height": 160
      },
      "absoluteRenderBounds": {
        "x": 2014.477294921875,
        "y": -14451.1318359375,
        "width": 258.060791015625,
        "height": 149.28125
      },
      "constraints": {
        "vertical": "TOP",
        "horizontal": "LEFT"
      },
      "layoutAlign": "INHERIT",
      "layoutGrow": 1,
      "layoutSizingHorizontal": "FILL",
      "layoutSizingVertical": "HUG",
      "characters": "Longer-figma-file-name-here-figma-file-name-here Longer-figma-file-name-here-figma-file-name-hereLonger-figma-file-name-here-figma-file-name-here Longer-figma-file-name-here-figma-file-name-here Longer-figma-file-name-here-figma-file-name-hereLonger-figma-file-name-here-figma-file-name-here",
      "characterStyleOverrides": [],
      "styleOverrideTable": {},
      "lineTypes": [
        "NONE"
      ],
      "lineIndentations": [
        0
      ],
      "style": {
        "fontFamily": "Inter",
        "fontPostScriptName": null,
        "fontStyle": "Light",
        "fontWeight": 300,
        "textAutoResize": "HEIGHT",
        "fontSize": 12,
        "textAlignHorizontal": "LEFT",
        "textAlignVertical": "CENTER",
        "letterSpacing": 0,
        "lineHeightPx": 20,
        "lineHeightPercent": 137.71517944335938,
        "lineHeightPercentFontSize": 166.6666717529297,
        "lineHeightUnit": "PIXELS"
      },
      "layoutVersion": 4,
      "effects": [],
      "interactions": []
    }
  ],
  "blendMode": "PASS_THROUGH",
  "clipsContent": false,
  "background": [
    {
      "blendMode": "NORMAL",
      "visible": false,
      "type": "SOLID",
      "color": {
        "r": 1,
        "g": 1,
        "b": 1,
        "a": 1
      }
    }
  ],
  "fills": [
    {
      "blendMode": "NORMAL",
      "visible": false,
      "type": "SOLID",
      "color": {
        "r": 1,
        "g": 1,
        "b": 1,
        "a": 1
      }
    }
  ],
  "strokes": [],
  "strokeWeight": 1,
  "strokeAlign": "INSIDE",
  "backgroundColor": {
    "r": 0,
    "g": 0,
    "b": 0,
    "a": 0
  },
  "layoutMode": "HORIZONTAL",
  "itemSpacing": 8,
  "primaryAxisSizingMode": "FIXED",
  "counterAxisAlignItems": "CENTER",
  "primaryAxisAlignItems": "CENTER",
  "layoutWrap": "NO_WRAP",
  "absoluteBoundingBox": {
    "x": 2014,
    "y": -14456,
    "width": 260,
    "height": 160
  },
  "absoluteRenderBounds": {
    "x": 2014,
    "y": -14456,
    "width": 260,
    "height": 160
  },
  "constraints": {
    "vertical": "TOP",
    "horizontal": "LEFT"
  },
  "layoutAlign": "INHERIT",
  "layoutGrow": 0,
  "layoutSizingHorizontal": "FIXED",
  "layoutSizingVertical": "HUG",
  "effects": [],
  "interactions": []
}