{
  "id": "68:1212",
  "name": "Frame 45",
  "type": "FRAME",
  "scrollBehavior": "SCROLLS",
  "children": [
    {
      "id": "68:1213",
      "name": "div.button-conta",
      "type": "TEXT",
      "scrollBehavior": "SCROLLS",
      "blendMode": "PASS_THROUGH",
      "fills": [
        {
          "blendMode": "NORMAL",
          "type": "SOLID",
          "color": {
            "r": 0,
            "g": 0,
            "b": 0,
            "a": 1
          }
        }
      ],
      "strokes": [],
      "strokeWeight": 1,
      "strokeAlign": "OUTSIDE",
      "absoluteBoundingBox": {
        "x": 9375,
        "y": -13760,
        "width": 187,
        "height": 21
      },
      "absoluteRenderBounds": {
        "x": 9375.9033203125,
        "y": -13755.7958984375,
        "width": 30.63671875,
        "height": 11.9892578125
      },
      "constraints": {
        "vertical": "TOP",
        "horizontal": "LEFT"
      },
      "layoutAlign": "INHERIT",
      "layoutGrow": 0,
      "layoutSizingHorizontal": "FIXED",
      "layoutSizingVertical": "FIXED",
      "characters": "CSS",
      "characterStyleOverrides": [],
      "styleOverrideTable": {},
      "lineTypes": [
        "NONE"
      ],
      "lineIndentations": [
        0
      ],
      "style": {
        "fontFamily": "Inter",
        "fontPostScriptName": null,
        "fontStyle": "Medium",
        "fontWeight": 500,
        "fontSize": 16,
        "textAlignHorizontal": "LEFT",
        "textAlignVertical": "CENTER",
        "letterSpacing": 0,
        "lineHeightPx": 19.363636016845703,
        "lineHeightPercent": 100,
        "lineHeightUnit": "INTRINSIC_%"
      },
      "layoutVersion": 4,
      "effects": [],
      "interactions": []
    }
  ],
  "blendMode": "PASS_THROUGH",
  "clipsContent": false,
  "background": [],
  "fills": [],
  "strokes": [],
  "strokeWeight": 1,
  "strokeAlign": "INSIDE",
  "backgroundColor": {
    "r": 0,
    "g": 0,
    "b": 0,
    "a": 0
  },
  "layoutMode": "HORIZONTAL",
  "itemSpacing": 8,
  "primaryAxisSizingMode": "FIXED",
  "counterAxisAlignItems": "CENTER",
  "paddingLeft": 16,
  "paddingRight": 16,
  "paddingTop": 8,
  "paddingBottom": 8,
  "layoutWrap": "NO_WRAP",
  "absoluteBoundingBox": {
    "x": 9359,
    "y": -13768,
    "width": 272,
    "height": 37
  },
  "absoluteRenderBounds": {
    "x": 9359,
    "y": -13768,
    "width": 272,
    "height": 37
  },
  "constraints": {
    "vertical": "TOP",
    "horizontal": "LEFT"
  },
  "layoutAlign": "STRETCH",
  "layoutGrow": 0,
  "layoutSizingHorizontal": "FILL",
  "layoutSizingVertical": "HUG",
  "effects": [],
  "interactions": []
}